komponents/cli.py
komponents/executor/__init__.py
komponents/executor/execute.py
komponents/executor/k8s.py
komponents/executor/utils.py
komponents/generator/__init__.py
komponents/generator/generate.py
komponents-1.2.dist-info/METADATA
komponents-1.2.dist-info/WHEEL
komponents-1.2.dist-info/entry_points.txt
komponents-1.2.dist-info/top_level.txt
komponents-1.2.dist-info/RECORD
