Metadata-Version: 2.1
Name: komponents
Version: 1.2
Summary: Generates Kubeflow Components from Kubernetes CRD specifications
Home-page: UNKNOWN
Author: David Farr
Author-email: david_farr@intuit.com
License: UNKNOWN
Platform: UNKNOWN
Requires-Dist: cachetools (==4.2.4)
Requires-Dist: certifi (==2021.10.8)
Requires-Dist: charset-normalizer (==2.0.7)
Requires-Dist: google-auth (==2.3.3)
Requires-Dist: idna (==3.3)
Requires-Dist: kubernetes (==19.15.0)
Requires-Dist: oauthlib (==3.1.1)
Requires-Dist: pyasn1 (==0.4.8)
Requires-Dist: pyasn1-modules (==0.2.8)
Requires-Dist: python-dateutil (==2.8.2)
Requires-Dist: PyYAML (==6.0)
Requires-Dist: requests (==2.26.0)
Requires-Dist: requests-oauthlib (==1.3.0)
Requires-Dist: rsa (==4.7.2)
Requires-Dist: six (==1.16.0)
Requires-Dist: urllib3 (==1.26.7)
Requires-Dist: websocket-client (==1.2.1)
